setup.py
yoctol_utils/__init__.py
yoctol_utils/hash.py
yoctol_utils.egg-info/PKG-INFO
yoctol_utils.egg-info/SOURCES.txt
yoctol_utils.egg-info/dependency_links.txt
yoctol_utils.egg-info/requires.txt
yoctol_utils.egg-info/top_level.txt