Metadata-Version: 1.1
Name: yoctol-utils
Version: 0.1.0
Summary: A pip package
Home-page: UNKNOWN
Author: cph
Author-email: UNKNOWN
License: MIT
Platform: UNKNOWN
Classifier: Programming Language :: Python
Classifier: Programming Language :: Python :: 3.5
